[
  {
    "id": 1,
    "name": "Marcus",
    "total_wins": 13,
    "current_wins": 4,
    "trophies": 0,
    "path": "/assets/images/avatars/marcus.jpg"
  },
  {
    "id": 2,
    "name": "Bernardo",
    "total_wins": 19,
    "current_wins": 4,
    "trophies": 1,
    "path": "/assets/images/avatars/bernardo.jpg"
  },
  {
    "id": 3,
    "name": "Isaac",
    "total_wins": 13,
    "current_wins": 1,
    "trophies": 0,
    "path": "/assets/images/avatars/isaac.jpg"
  },
  {
    "id": 4,
    "name": "Matheus",
    "total_wins": 6,
    "current_wins": 1,
    "trophies": 0,
    "path": "/assets/images/avatars/matheus.jpg"
  },
  {
    "id": 5,
    "name": "Pedro",
    "total_wins": 18,
    "current_wins": 5,
    "trophies": 1,
    "path": "/assets/images/avatars/pedro.jpg"
  },
  {
    "id": 6,
    "name": "Rafa Perdomo",
    "total_wins": 18,
    "current_wins": 7,
    "trophies": 0,
    "path": "/assets/images/avatars/"
  },
  {
    "id": 7,
    "name": "Thiago",
    "total_wins": 8,
    "current_wins": 3,
    "trophies": 0,
    "path": "/assets/images/avatars/thiago.jpg"
  },
  {
    "id": 8,
    "name": "Ulisses",
    "total_wins": 4,
    "current_wins": 3,
    "trophies": 0,
    "path": "/assets/images/avatars/ulisses.jpg"
  },
  {
    "id": 9,
    "name": "Mateus Basilio",
    "total_wins": 4,
    "current_wins": 2,
    "trophies": 0,
    "path": "/assets/images/avatars/"
  },
  {
    "id": 10,
    "name": "Alencar",
    "total_wins": 1,
    "current_wins": 0,
    "trophies": 0,
    "path": "/assets/images/avatars/"
  }
]
